__init__.py
FLYCOP/COMETSSimulator.py
FLYCOP/Consortia.py
FLYCOP/FLYCOP2.py
FLYCOP/Fitness.py
FLYCOP/MMODESSimulator.py
FLYCOP/ObjectiveFunction.py
FLYCOP/Optimizer.py
FLYCOP/OptimizerFactory.py
FLYCOP/SKoptOptimizer.py
FLYCOP/SMAC3Optimizer.py
FLYCOP/Simulator.py
FLYCOP/SimulatorFactory.py
FLYCOP/SurfinFBASimulator.py
FLYCOP/__init__.py
FLYCOP/dFBASimulator.py
FLYCOP/example.py
FLYCOP/version.py
FLYCOP-1.6.0.dist-info/LICENSE
FLYCOP-1.6.0.dist-info/METADATA
FLYCOP-1.6.0.dist-info/WHEEL
FLYCOP-1.6.0.dist-info/top_level.txt
FLYCOP-1.6.0.dist-info/RECORD
