Metadata-Version: 2.1
Name: FLYCOP
Version: 1.6.0
Summary: FLYCOP
Author-email: SBG Team <dsanleon@cnb.csic.es>
Project-URL: Homepage, https://github.com/SBGlab/FLYCOP
Project-URL: Issues, https://github.com/SBGlab/FLYCOP/issues
Classifier: Programming Language :: Python :: 3
Classifier: License :: OSI Approved :: MIT License
Classifier: Operating System :: POSIX :: Linux
Classifier: Topic :: Scientific/Engineering :: Bio-Informatics
Requires-Python: >=3.8
License-File: LICENSE
